virt_up/__init__.py
virt_up/__main__.py
virt_up/cli.py
virt_up/instance.py
virt_up/cookiecutter/config/cookiecutter.json
virt_up/cookiecutter/config/{{cookiecutter.config_directory}}/settings.cfg
virt_up/cookiecutter/config/{{cookiecutter.config_directory}}/playbooks/openafs-devel.yaml
virt_up/cookiecutter/config/{{cookiecutter.config_directory}}/playbooks/update.yaml
virt_up/cookiecutter/config/{{cookiecutter.config_directory}}/scripts/fixup-netplan-netcfg.sh
virt_up/cookiecutter/config/{{cookiecutter.config_directory}}/scripts/fixup-network-interfaces.sh
virt_up/cookiecutter/config/{{cookiecutter.config_directory}}/templates.d/centos.cfg
virt_up/cookiecutter/config/{{cookiecutter.config_directory}}/templates.d/debian.cfg
virt_up/cookiecutter/config/{{cookiecutter.config_directory}}/templates.d/default.cfg
virt_up/cookiecutter/config/{{cookiecutter.config_directory}}/templates.d/fedora.cfg
virt_up/cookiecutter/config/{{cookiecutter.config_directory}}/templates.d/opensuse.cfg
virt_up/cookiecutter/config/{{cookiecutter.config_directory}}/templates.d/ubuntu.cfg
virt_up/cookiecutter/template/cookiecutter.json
virt_up/cookiecutter/template/{{cookiecutter.templates_directory}}/{{cookiecutter.template_file}}
virt_up-2.2.0.dist-info/LICENSE
virt_up-2.2.0.dist-info/METADATA
virt_up-2.2.0.dist-info/WHEEL
virt_up-2.2.0.dist-info/entry_points.txt
virt_up-2.2.0.dist-info/top_level.txt
virt_up-2.2.0.dist-info/RECORD
