Metadata-Version: 2.1
Name: virt-up
Version: 2.2.0
Summary: Create virtual machines quickly with virt-builder.
Home-page: https://github.com/meffie/virt-up
Author: Michael Meffie
Author-email: mmeffie@sinenomine.net
License: BSD
Platform: UNKNOWN
Classifier: Development Status :: 4 - Beta
Classifier: Environment :: Console
Classifier: Intended Audience :: Developers
Classifier: License :: OSI Approved :: BSD License
Classifier: Operating System :: POSIX
Classifier: Programming Language :: Python :: 3
Classifier: Topic :: Software Development
Requires-Dist: Click
Requires-Dist: cookiecutter
Requires-Dist: libvirt-python
Requires-Dist: sh
